ailib/__init__.py
ailib/ai_models.py
ailib/models.py
tests/__init__.py
tests/test_ai_lib.py
modular_ai-0.1.2.dist-info/LICENSE
modular_ai-0.1.2.dist-info/METADATA
modular_ai-0.1.2.dist-info/WHEEL
modular_ai-0.1.2.dist-info/top_level.txt
modular_ai-0.1.2.dist-info/RECORD
