Metadata-Version: 2.1
Name: modular-ai
Version: 0.1.2
Summary: A library for interacting with various AI models
Home-page: https://github.com/HarveyGW/modular-ai
Author: HarveyGW
Author-email: harvey@hwfreelance.co.uk
License: UNKNOWN
Platform: UNKNOWN
Classifier: Programming Language :: Python :: 3
Classifier: License :: OSI Approved :: MIT License
Classifier: Operating System :: OS Independent
Requires-Python: >=3.6
License-File: LICENSE
Requires-Dist: anthropic
Requires-Dist: python-dotenv
Requires-Dist: requests
